LICENSE.md
MANIFEST.in
README.md
setup.py
agas/__init__.py
agas/_from_numpy.py
agas/_from_pandas.py
agas/constants.py
agas.egg-info/PKG-INFO
agas.egg-info/SOURCES.txt
agas.egg-info/dependency_links.txt
agas.egg-info/requires.txt
agas.egg-info/top_level.txt
tests/__init__.py
tests/test_from_numpy_api.py
tests/test_from_numpy_basics.py
tests/test_from_pandas_api.py