Metadata-Version: 2.1
Name: agas
Version: 0.0.1
Summary: Agas is a small Python library for pairing similar (or dissimilar) data series.
Home-page: https://github.com/EitanHemed/agas
Author: Eitan Hemed
Author-email: Eitan.Hemed@gmail.com
Project-URL: Bug Tracker, https://github.com/EitanHemed/agas/issues
Classifier: Intended Audience :: Science/Research
Classifier: Operating System :: OS Independent
License-File: LICENSE.md
